<?xml version="1.0" encoding="UTF-8"?>
<schuhscout> <!--Einigermassen sinnvolle Schachtelung? Wie Wuerdest du es machen?-->
    <schuhkategorien>
	    <kategorie id="1" name="Sportschuhe" />
	    <kategorie id="2" name="Laufschuhe" />
	    <kategorie id="3" name="Trekkingschuhe" />
    </schuhkategorien>
    <schuhkatalog>
        <kategorie id="1">
            <artikel id="sport1"> <!--id oder besser class?-->
                <name>Speed Run</name>
                <zielgruppe>Herren</zielgruppe>
                <groesse_von>40</groesse_von>
                <groesse_bis>48</groesse_bis>
                <marke>Nike</marke>
                <farbe>Blau</farbe>
            </artikel>
            <artikel id="sport2">
                <name>Light Blue</name>
                <zielgruppe>Herren</zielgruppe>
                <groesse_von>40</groesse_von>
                <groesse_bis>48</groesse_bis>
                <marke>Nike</marke>
                <farbe>Blau</farbe>
            </artikel>
            <artikel id="sport3">
                <name>Speed Run</name>
                <zielgruppe>Kinder</zielgruppe>
                <groesse_von>28</groesse_von>
                <groesse_bis>34</groesse_bis>
                <marke>Adidas</marke>
                <farbe>Blau</farbe>
            </artikel>
            <artikel id="sport4">
                <name>Quick Speed</name>
                <zielgruppe>Herren</zielgruppe>
                <groesse_von>40</groesse_von>
                <groesse_bis>48</groesse_bis>
                <marke>Adidas</marke>
                <farbe>Schwarz</farbe>
            </artikel>
            <artikel id="sport5">
                <name>Cyan Flash</name>
                <zielgruppe>Herren</zielgruppe>
                <groesse_von>40</groesse_von>
                <groesse_bis>48</groesse_bis>
                <marke>Nike</marke>
                <farbe>Schwarz</farbe>
            </artikel>
            <artikel id="sport6">
                <name>Gowak</name>
                <zielgruppe>Damen</zielgruppe>
                <groesse_von>35</groesse_von>
                <groesse_bis>40</groesse_bis>
                <marke>Skechers</marke>
                <farbe>Grün</farbe>
            </artikel>
            <artikel id="sport7">
                <name>Lightgear</name>
                <zielgruppe>Damen</zielgruppe>
                <groesse_von>35</groesse_von>
                <groesse_bis>40</groesse_bis>
                <marke>Skechers</marke>
                <farbe>Grau</farbe>
            </artikel>
            <artikel id="sport8">
                <name>Mette</name>
                <zielgruppe>Herren</zielgruppe>
                <groesse_von>40</groesse_von>
                <groesse_bis>48</groesse_bis>
                <marke>Asics</marke>
                <farbe>Grau</farbe>
            </artikel>
            <artikel id="sport9">
                <name>Flex Sole</name>
                <zielgruppe>Herren</zielgruppe>
                <groesse_von>40</groesse_von>
                <groesse_bis>48</groesse_bis>
                <marke>Skechers</marke>
                <farbe>Braun</farbe>
            </artikel>
            <artikel id="sport10">
                <name>Green Lantern</name>
                <zielgruppe>Herren</zielgruppe>
                <groesse_von>40</groesse_von>
                <groesse_bis>48</groesse_bis>
                <marke>Nike</marke>
                <farbe>Grün</farbe>
            </artikel>
        </kategorie>
        <kategorie id="2">
            <artikel id="lauf1">
                <name></name>
                <zielgruppe></zielgruppe>
                <groesse></groesse>
                <marke></marke>
                <farbe></farbe>
            </artikel>
            <artikel id="lauf2">
                <name></name>
                <zielgruppe></zielgruppe>
                <groesse></groesse>
                <marke></marke>
                <farbe></farbe>
            </artikel>
            <artikel id="lauf3">
                <name></name>
                <zielgruppe></zielgruppe>
                <groesse></groesse>
                <marke></marke>
                <farbe></farbe>
            </artikel>
        </kategorie>
        <kategorie id="3">
            <artikel id="trekk1">
                <name></name>
                <zielgruppe></zielgruppe>
                <groesse></groesse>
                <marke></marke>
                <farbe></farbe>
            </artikel>
            <artikel id="trekk2">
                <name></name>
                <zielgruppe></zielgruppe>
                <groesse></groesse>
                <marke></marke>
                <farbe></farbe>
            </artikel>
            <artikel id="trekk3">
                <name></name>
                <zielgruppe></zielgruppe>
                <groesse></groesse>
                <marke></marke>
                <farbe></farbe>
            </artikel>
        </kategorie>
    </schuhkatalog>
</schuhscout>
